{
	"configurations" : 
	[
		{
			"directories" : 
			[
				{
					"build" : ".",
					"childIndexes" : 
					[
						1
					],
					"hasInstallRule" : true,
					"jsonFile" : "directory-.-Debug-f5ebdc15457944623624.json",
					"minimumCMakeVersion" : 
					{
						"string" : "3.11"
					},
					"projectIndex" : 0,
					"source" : ".",
					"targetIndexes" : 
					[
						0,
						5,
						6
					]
				},
				{
					"build" : "_deps/googletest-build",
					"childIndexes" : 
					[
						2
					],
					"hasInstallRule" : true,
					"jsonFile" : "directory-_deps.googletest-build-Debug-fa1b18db30f420365ea4.json",
					"minimumCMakeVersion" : 
					{
						"string" : "3.5"
					},
					"parentIndex" : 0,
					"projectIndex" : 1,
					"source" : "cmake-build-debug/_deps/googletest-src"
				},
				{
					"build" : "_deps/googletest-build/googlemock",
					"childIndexes" : 
					[
						3
					],
					"hasInstallRule" : true,
					"jsonFile" : "directory-_deps.googletest-build.googlemock-Debug-31a54d377b384cc38fbe.json",
					"minimumCMakeVersion" : 
					{
						"string" : "3.5"
					},
					"parentIndex" : 1,
					"projectIndex" : 2,
					"source" : "cmake-build-debug/_deps/googletest-src/googlemock",
					"targetIndexes" : 
					[
						1,
						2
					]
				},
				{
					"build" : "_deps/googletest-build/googletest",
					"hasInstallRule" : true,
					"jsonFile" : "directory-_deps.googletest-build.googletest-Debug-a091d3d4c1720dfc82ff.json",
					"minimumCMakeVersion" : 
					{
						"string" : "3.5"
					},
					"parentIndex" : 2,
					"projectIndex" : 3,
					"source" : "cmake-build-debug/_deps/googletest-src/googletest",
					"targetIndexes" : 
					[
						3,
						4
					]
				}
			],
			"name" : "Debug",
			"projects" : 
			[
				{
					"childIndexes" : 
					[
						1
					],
					"directoryIndexes" : 
					[
						0
					],
					"name" : "lab5_os_named_pipes",
					"targetIndexes" : 
					[
						0,
						5,
						6
					]
				},
				{
					"childIndexes" : 
					[
						2
					],
					"directoryIndexes" : 
					[
						1
					],
					"name" : "googletest-distribution",
					"parentIndex" : 0
				},
				{
					"childIndexes" : 
					[
						3
					],
					"directoryIndexes" : 
					[
						2
					],
					"name" : "gmock",
					"parentIndex" : 1,
					"targetIndexes" : 
					[
						1,
						2
					]
				},
				{
					"directoryIndexes" : 
					[
						3
					],
					"name" : "gtest",
					"parentIndex" : 2,
					"targetIndexes" : 
					[
						3,
						4
					]
				}
			],
			"targets" : 
			[
				{
					"directoryIndex" : 0,
					"id" : "client::@6890427a1f51a3e7e1df",
					"jsonFile" : "target-client-Debug-6500409e6f73d6552755.json",
					"name" : "client",
					"projectIndex" : 0
				},
				{
					"directoryIndex" : 2,
					"id" : "gmock::@0f7bb11d64f3678238c7",
					"jsonFile" : "target-gmock-Debug-5d08f02e99a073443a77.json",
					"name" : "gmock",
					"projectIndex" : 2
				},
				{
					"directoryIndex" : 2,
					"id" : "gmock_main::@0f7bb11d64f3678238c7",
					"jsonFile" : "target-gmock_main-Debug-b1e62de56e709ff904c5.json",
					"name" : "gmock_main",
					"projectIndex" : 2
				},
				{
					"directoryIndex" : 3,
					"id" : "gtest::@1ea2dfc0605fe3ab2a3f",
					"jsonFile" : "target-gtest-Debug-917b5ec5406d45662d57.json",
					"name" : "gtest",
					"projectIndex" : 3
				},
				{
					"directoryIndex" : 3,
					"id" : "gtest_main::@1ea2dfc0605fe3ab2a3f",
					"jsonFile" : "target-gtest_main-Debug-7208f96bc53178ce5a6b.json",
					"name" : "gtest_main",
					"projectIndex" : 3
				},
				{
					"directoryIndex" : 0,
					"id" : "server::@6890427a1f51a3e7e1df",
					"jsonFile" : "target-server-Debug-8bffeaf3e9e9d934adb3.json",
					"name" : "server",
					"projectIndex" : 0
				},
				{
					"directoryIndex" : 0,
					"id" : "test_employee::@6890427a1f51a3e7e1df",
					"jsonFile" : "target-test_employee-Debug-5c619219c33fe92624e1.json",
					"name" : "test_employee",
					"projectIndex" : 0
				}
			]
		}
	],
	"kind" : "codemodel",
	"paths" : 
	{
		"build" : "/Users/olegraytsev/Documents/bsu/osy/lab5/cmake-build-debug",
		"source" : "/Users/olegraytsev/Documents/bsu/osy/lab5"
	},
	"version" : 
	{
		"major" : 2,
		"minor" : 7
	}
}
